example_isort_sorting_plugin.py
example_isort_sorting_plugin-0.1.0.dist-info/WHEEL
example_isort_sorting_plugin-0.1.0.dist-info/METADATA
example_isort_sorting_plugin-0.1.0.dist-info/entry_points.txt
example_isort_sorting_plugin-0.1.0.dist-info/RECORD
